gs_api_wrapper/__init__.py
gs_api_wrapper/audit.py
gs_api_wrapper/client.py
gs_api_wrapper/fetch_data.py
gs_api_wrapper-1.0.2.dist-info/METADATA
gs_api_wrapper-1.0.2.dist-info/WHEEL
gs_api_wrapper-1.0.2.dist-info/top_level.txt
gs_api_wrapper-1.0.2.dist-info/RECORD
