Metadata-Version: 2.1
Name: gs-api-wrapper
Version: 1.0.2
Summary: A Python wrapper for GoldenSource API
Home-page: https://github.com/nqadirgs/gs-api-wrapper
Author: Nasar Qadir
Author-email: nqadir@thegoldensource.com
Classifier: Programming Language :: Python :: 3
Classifier: License :: OSI Approved :: MIT License
Classifier: Operating System :: OS Independent
Requires-Python: >=3.6
Requires-Dist: requests>=2.25.0
